[
    {
        "model": "mcpressureapi.servicetype",
        "pk": 1,
        "fields": {
            "label": "scheduled",
            "description": "Using pressure to wash grim and debris from sidewalks",
            "price": 250,
            "equipment_id": 1,
            "name": "Power Wash"
        }
    },
    {
        "model": "mcpressureapi.servicetype",
        "pk": 1,
        "fields": {
            "label": "scheduled",
            "description": "Using pressure to wash grim and debris from sidewalks",
            "price": 250,
            "equipment_id": 1,
            "name": "Power Wash"
        }
    },
    {
        "model": "mcpressureapi.servicetype",
        "pk": 1,
        "fields": {
            "label": "scheduled",
            "description": "Using pressure to wash grim and debris from sidewalks",
            "price": 250,
            "equipment_id": 1,
            "name": "Power Wash"
        }
    }
]